packagetest-0.1.0.dist-info/DESCRIPTION.rst
packagetest-0.1.0.dist-info/METADATA
packagetest-0.1.0.dist-info/RECORD
packagetest-0.1.0.dist-info/WHEEL
packagetest-0.1.0.dist-info/metadata.json
packagetest-0.1.0.dist-info/top_level.txt
src/__init__.py
src/start.py
