Metadata-Version: 1.0
Name: packagetest
Version: 0.1.0
Summary: Sample package for Python-Guide.org
Home-page: https://github.com/jeffrichard/wiab
Author: Jeff Richard
Author-email: jeff@jeffrichard.com
License: Copyright (c) 2017, Jeff Richard
